Metadata-Version: 1.0
Name: TracHtGroupEditorPlugin
Version: 2.0.1
Summary: HT Group Editor plugin for Trac
Home-page: http://trac-hacks.org/wiki/TracGroupsEditor
Author: Robert Martin
Author-email: robert.martin@arqiva.com
License: GPL
Platform: UNKNOWN
